mux4x1.vhd
library IEEE;
use IEEE.std_logic_1164.all;

entity mux4x1 is 
    port(
        entrada0, entrada1, entrada2, entrada3 : in std_logic;
        selector : in std_logic_vector(1 downto 0);
        salida : out std_logic
    );
end mux4x1;

architecture A_mux4x1 of mux4x1 is
begin
    with selector select
        salida <= entrada0 when "00",
                  entrada1 when "01",
                  entrada2 when "10",
                  entrada3 when others;
end A_mux4x1;

shifter.vhd
library IEEE;
use IEEE.std_logic_1164.all;

entity shifter is 
    port (
        A : in std_logic_vector(7 downto 0);
        S : in std_logic_vector(1 downto 0);
        R : out std_logic_vector(7 downto 0)
    );
end shifter;

architecture arch of shifter is
    component mux4x1 is
        port (
            entrada0, entrada1, entrada2, entrada3 : in std_logic;
            selector : in std_logic_vector(1 downto 0);
            salida : out std_logic
        );
    end component;

begin
    mux7: mux4x1 port map('0' , A(6), A(0), A(6), S, R(7));
    mux6: mux4x1 port map(A(7), A(5), A(7), A(5), S, R(6));
    mux5: mux4x1 port map(A(6), A(4), A(6), A(4), S, R(5));
    mux4: mux4x1 port map(A(5), A(3), A(5), A(3), S, R(4));
    mux3: mux4x1 port map(A(4), A(2), A(4), A(2), S, R(3));
    mux2: mux4x1 port map(A(3), A(1), A(3), A(1), S, R(2));
    mux1: mux4x1 port map(A(2), A(0), A(2), A(0), S, R(1));
    mux0: mux4x1 port map(A(1), '0' , A(1), A(7), S, R(0));
end arch;

Unidad_Logica.vhd
library IEEE;
use IEEE.std_logic_1164.all;

entity Unidad_Logica is
    port (
        A, B: in std_logic_vector(7 downto 0);
        S: in std_logic_vector(2 downto 0);
        R: out std_logic_vector(7 downto 0)
    );
end Unidad_Logica;

architecture arch of Unidad_Logica is
begin
    R <= 
        -- NOT A
        not A when S = "000" else
        -- NOT B
        not B when S = "001" else
        -- A AND B 
        (A and B) when S = "010" else
        -- A OR B
        (A or B) when S = "011" else
        -- A NAND B 
        not (A and B) when S = "100" else
        -- A NOR B
        not (A or B) when S = "101" else
        -- A XOR B
        (A xor B) when S = "110" else
        -- A XNOR B
        not (A xor B);
end arch;

Unidad_Funcional/Unidad_Aritmetica/FA.vhd
--Full Adder
library IEEE;
use IEEE.std_logic_1164.all;

 entity FA is
   --a y b entradas, cin acarreo de entrada.
   --r y cout salida y acarreo de salida.
   port (a, b, cin: in std_logic;
         r, cout: out std_logic);
 end FA;
 
 architecture Ar_FA of FA is
 begin
   cout <= (a and cin) or (a and b) or (b and cin);
   r <= (a xor (b xor cin));
 end Ar_FA;

Unidad_Funcional/Unidad_Aritmetica/Sumador8Bits.vhd
--Sumador de 8 bits empleando FA y HA
--El sumador posee bit de acarreo de entrada y salida

library IEEE;
use IEEE.std_logic_1164.all;


 entity Sumador8Bits is
   --A y B entradas de 8 bits, cin entrada de un bit.
   --R y cout salida de 8 bits y acarreo de salida.
   port (A, B: in std_logic_vector (7 downto 0);
         cin: in std_logic;
         R: out std_logic_vector (7 downto 0); 
         cout: out std_logic;
         v: out std_logic);
 end Sumador8Bits;
 
 architecture Ar_Sumador8Bits of Sumador8Bits is
   component FA
     port (a, b, cin: in std_logic;
           r, cout: out std_logic);
   end component;

 signal C : std_logic_vector (6 downto 0);
 signal w : std_logic;
 begin
   Sumador0: FA port map (A(0), B(0), cin, R(0), C(0)); 
   Sumador1: FA port map (A(1), B(1), C(0), R(1), C(1)); 
   Sumador2: FA port map (A(2), B(2), C(1), R(2), C(2)); 
   Sumador3: FA port map (A(3), B(3), C(2), R(3), C(3)); 
   Sumador4: FA port map (A(4), B(4), C(3), R(4), C(4)); 
   Sumador5: FA port map (A(5), B(5), C(4), R(5), C(5)); 
   Sumador6: FA port map (A(6), B(6), C(5), R(6), C(6)); 
   Sumador7: FA port map (A(7), B(7), C(6), R(7), cout => w); 
   cout <= w;
   v <= w xor C(6);
 end Ar_Sumador8Bits;

Unidad_Aritmetica.vhd
library IEEE;
use IEEE.std_logic_1164.all;

entity Unidad_Aritmetica is
	port (
		A, B: in std_logic_vector(7 downto 0);
		S : in std_logic_vector(2 downto 0);
		R: out std_logic_vector(7 downto 0);
		c, v, z, sig: out std_logic
	);
end Unidad_Aritmetica;

architecture arch of Unidad_Aritmetica is
	component Sumador8Bits is
		port (
			A, B: in std_logic_vector (7 downto 0);
			cin: in std_logic;
			R: out std_logic_vector (7 downto 0);
			cout: out std_logic;
			v: out std_logic
		);
	end component Sumador8Bits;

	signal Ap, Bp: std_logic_vector(7 downto 0);
	signal cin: std_logic;
	signal R_aux: std_logic_vector(7 downto 0);

	begin

	-- Ap = AS2’S1’ + AS0’ + S2S1’S0
	Ap(0) <= (A(0) and not(S(2)) and not(S(1))) or (A(0) and not(S(0))) or (S(2) and not(S(1)) and S(0));
    Ap(1) <= (A(1) and not(S(2)) and not(S(1))) or (A(1) and not(S(0))) or (S(2) and not(S(1)) and S(0));
    Ap(2) <= (A(2) and not(S(2)) and not(S(1))) or (A(2) and not(S(0))) or (S(2) and not(S(1)) and S(0));
    Ap(3) <= (A(3) and not(S(2)) and not(S(1))) or (A(3) and not(S(0))) or (S(2) and not(S(1)) and S(0));
    Ap(4) <= (A(4) and not(S(2)) and not(S(1))) or (A(4) and not(S(0))) or (S(2) and not(S(1)) and S(0));
    Ap(5) <= (A(5) and not(S(2)) and not(S(1))) or (A(5) and not(S(0))) or (S(2) and not(S(1)) and S(0));
    Ap(6) <= (A(6) and not(S(2)) and not(S(1))) or (A(6) and not(S(0))) or (S(2) and not(S(1)) and S(0));
    Ap(7) <= (A(7) and not(S(2)) and not(S(1))) or (A(7) and not(S(0))) or (S(2) and not(S(1)) and S(0));

	-- Bp = BS2’S1’S0’ + B’S2’S1’S0 + BS1S0 + S2S1’S0’ + BS2S0
	Bp(0) <= ((B(0) and not(S(2)) and not(S(1)) and not(S(0))) or (not(B(0)) and not(S(2)) and not(S(1)) and S(0)) or (B(0) and S(1) and S(0)) or (S(2) and not(S(1)) and not(S(0))) or (B(0) and S(2) and S(0)));
	Bp(1) <= ((B(1) and not(S(2)) and not(S(1)) and not(S(0))) or (not(B(1)) and not(S(2)) and not(S(1)) and S(0)) or (B(1) and S(1) and S(0)) or (S(2) and not(S(1)) and not(S(0))) or (B(1) and S(2) and S(0)));
	Bp(2) <= ((B(2) and not(S(2)) and not(S(1)) and not(S(0))) or (not(B(2)) and not(S(2)) and not(S(1)) and S(0)) or (B(2) and S(1) and S(0)) or (S(2) and not(S(1)) and not(S(0))) or (B(2) and S(2) and S(0)));
	Bp(3) <= ((B(3) and not(S(2)) and not(S(1)) and not(S(0))) or (not(B(3)) and not(S(2)) and not(S(1)) and S(0)) or (B(3) and S(1) and S(0)) or (S(2) and not(S(1)) and not(S(0))) or (B(3) and S(2) and S(0)));
	Bp(4) <= ((B(4) and not(S(2)) and not(S(1)) and not(S(0))) or (not(B(4)) and not(S(2)) and not(S(1)) and S(0)) or (B(4) and S(1) and S(0)) or (S(2) and not(S(1)) and not(S(0))) or (B(4) and S(2) and S(0)));
	Bp(5) <= ((B(5) and not(S(2)) and not(S(1)) and not(S(0))) or (not(B(5)) and not(S(2)) and not(S(1)) and S(0)) or (B(5) and S(1) and S(0)) or (S(2) and not(S(1)) and not(S(0))) or (B(5) and S(2) and S(0)));
	Bp(6) <= ((B(6) and not(S(2)) and not(S(1)) and not(S(0))) or (not(B(6)) and not(S(2)) and not(S(1)) and S(0)) or (B(6) and S(1) and S(0)) or (S(2) and not(S(1)) and not(S(0))) or (B(6) and S(2) and S(0)));
	Bp(7) <= ((B(7) and not(S(2)) and not(S(1)) and not(S(0))) or (not(B(7)) and not(S(2)) and not(S(1)) and S(0)) or (B(7) and S(1) and S(0)) or (S(2) and not(S(1)) and not(S(0))) or (B(7) and S(2) and S(0)));

	--S2’S0 + S2’S1
	cin <= (not(S(2)) and S(0)) or (not(S(2)) and S(1));

	Sum: Sumador8Bits port map (Ap, Bp, cin, R_aux, c, v);


	R <= R_aux; -- Asignamos el resultado a la salida R

	-- Asignamos las señales de salida
	z <= '1' when R_aux = "00000000" else '0'; -- Z es '1' si R_internal es 0, '0' en caso contrario
	sig <= R_aux(7); -- El bit más significativo de R_internal es el bit de signo

end arch;

Unidad_Funcional.vhd
library IEEE;
use IEEE.std_logic_1164.all;

entity Unidad_Funcional is 
    port(
        A, B : in std_logic_vector(7 downto 0);
        S : in std_logic_vector(4 downto 0);
        R : out std_logic_vector(7 downto 0);
        carry, v, z, sig: out std_logic
    );
end Unidad_Funcional;

architecture arch of Unidad_Funcional is
    component Unidad_Aritmetica is 
        port (
            A, B: in std_logic_vector(7 downto 0);
            S : in std_logic_vector(2 downto 0);
            R: out std_logic_vector(7 downto 0);
            c, v, z, sig: out std_logic
        );
    end component;

    component Unidad_Logica is
        port (
            A, B: in std_logic_vector(7 downto 0);
            S: in std_logic_vector(2 downto 0);
            R: out std_logic_vector(7 downto 0)
        );
    end component;

    component shifter is
        port (
            A : in std_logic_vector(7 downto 0);
            S : in std_logic_vector(1 downto 0);
            R : out std_logic_vector(7 downto 0)
        );
    end component;

    signal arith_R : std_logic_vector(7 downto 0);
    signal logic_R : std_logic_vector(7 downto 0);
    signal shift_R : std_logic_vector(7 downto 0);
    signal selector : std_logic_vector(1 downto 0);

begin

    -- Instancias de los componentes
    UA: Unidad_Aritmetica port map(A, B, S(2 downto 0), arith_R, carry, v, z, sig);
    UL: Unidad_Logica port map(A, B, S(2 downto 0), logic_R);
    US: shifter port map(A, S(1 downto 0), shift_R);
    selector <= S(4 downto 3);

    R <= arith_R when selector = "00" else
         logic_R when selector = "01" else 
         shift_R when selector = "10" else 
         "00000000";

end arch;

Unidad_Funcional_tb.vhd
library IEEE;
use IEEE.std_logic_1164.all;

entity Unidad_Funcional_tb is
end Unidad_Funcional_tb;

architecture arch of Unidad_Funcional_tb is
    component Unidad_Funcional
        port(
            A, B : in std_logic_vector(7 downto 0);
            S : in std_logic_vector(4 downto 0);
            R : out std_logic_vector(7 downto 0);
            carry, v, z, sig: out std_logic
        );
    end component;


    
    signal A_tb, B_tb: std_logic_vector(7 downto 0);
    signal S_tb: std_logic_vector(4 downto 0);
    signal R_tb: std_logic_vector(7 downto 0);
    signal carry_tb, v_tb, z_tb, sig_tb: std_logic;

begin
    test: Unidad_Funcional port map (A => A_tb, B => B_tb, S => S_tb, R => R_tb, carry => carry_tb, v => v_tb, z => z_tb, sig => sig_tb);
    
    process
    begin
        A_tb <= (others => '0');
        B_tb <= (others => '0');
        S_tb <= (others => '0');
        
        -- Test case 1: SUMA A B
        A_tb <= "00000001";
        B_tb <= "00000010";
        S_tb <= "00000";
        wait for 10 ns;
        
        -- Test case 2: RESTA A B 
        A_tb <= "01010101";
        B_tb <= "10101010";
        S_tb <= "00001";
        wait for 10 ns;
        
        -- Test case 3: INC A
        A_tb <= "11001100";
        B_tb <= "00000000";
        S_tb <= "00010";
        wait for 10 ns;
        
        -- Test case 4: INC B
        A_tb <= "11111111";
        B_tb <= "00000000";
        S_tb <= "00011";
        wait for 10 ns;
        
        -- Test case 5: DEC A
        A_tb <= "00000001";
        B_tb <= "11111110";
        S_tb <= "00100";
        wait for 10 ns;
        
        -- Test case 6: DEC B
        A_tb <= "10101010";
        B_tb <= "01010101";
        S_tb <= "00101";
        wait for 10 ns;
        
        -- Test case 7: TRANSF A
        A_tb <= "01010101";
        B_tb <= "10101010";
        S_tb <= "00110";
        wait for 10 ns;
        
        -- Test case 8: TRANSF B
        A_tb <= "11110000";
        B_tb <= "00001111";
        S_tb <= "00111";
        wait for 10 ns;
        
        -- Test case 9: NOT A
        A_tb <= "11001100";
        B_tb <= "00110011";
        S_tb <= "01000";
        wait for 10 ns;
        
        -- Test case 10: NOT B
        A_tb <= "00110011";
        B_tb <= "11001100";
        S_tb <= "01001";
        wait for 10 ns;
        
        -- Test case 11: A AND B
        A_tb <= "11111111";
        B_tb <= "00000001";
        S_tb <= "01010";
        wait for 10 ns;
        
        -- Test case 12: A OR B
        A_tb <= "00000010";
        B_tb <= "11111111";
        S_tb <= "01011";
        wait for 10 ns;
        
        -- Test case 13: A NAND B 
        A_tb <= "10101010";
        B_tb <= "01010101";
        S_tb <= "01100";
        wait for 10 ns;
        
        -- Test case 14: A NOR C
        A_tb <= "01010101";
        B_tb <= "10101010";
        S_tb <= "01101";
        wait for 10 ns;
        
        -- Test case 15: A XOR B
        A_tb <= "00000001";
        B_tb <= "00000010";
        S_tb <= "01110";
        wait for 10 ns;
        
        -- Test case 16: A XNOR B
        A_tb <= "11111111";
        B_tb <= "11111111";
        S_tb <= "01111";
        wait for 10 ns;
        
        -- Test case 17: DES →
        A_tb <= "00000000";
        B_tb <= "00000001";
        S_tb <= "10000";
        wait for 10 ns;
        
        -- Test case 18: DES ←
        A_tb <= "11111111";
        B_tb <= "11111110";
        S_tb <= "10001";
        wait for 10 ns;
        
        -- Test case 19: ROT ⟳
        A_tb <= "00111100";
        B_tb <= "11000011";
        S_tb <= "10010";
        wait for 10 ns;
        
        -- Test case 20: ROT ⟲
        A_tb <= "01010101";
        B_tb <= "01010101";
        S_tb <= "10011";
        wait for 10 ns;
        
        wait;
    end process;

end arch;

Unidad_Funcional.vcd
$date
  Wed Jun 21 01:31:59 2023
$end
$version
  GHDL v0
$end
$timescale
  1 fs
$end
$scope module standard $end
$upscope $end
$scope module std_logic_1164 $end
$upscope $end
$scope module unidad_funcional_tb $end
$var reg 8 ! a_tb[7:0] $end
$var reg 8 " b_tb[7:0] $end
$var reg 5 # s_tb[4:0] $end
$var reg 8 $ r_tb[7:0] $end
$var reg 1 % carry_tb $end
$var reg 1 & v_tb $end
$var reg 1 ' z_tb $end
$var reg 1 ( sig_tb $end
$scope module test $end
$var reg 8 ) a[7:0] $end
$var reg 8 * b[7:0] $end
$var reg 5 + s[4:0] $end
$var reg 8 , r[7:0] $end
$var reg 1 - carry $end
$var reg 1 . v $end
$var reg 1 / z $end
$var reg 1 0 sig $end
$var reg 8 1 arith_r[7:0] $end
$var reg 8 2 logic_r[7:0] $end
$var reg 8 3 shift_r[7:0] $end
$var reg 2 4 selector[1:0] $end
$scope module ua $end
$var reg 8 5 a[7:0] $end
$var reg 8 6 b[7:0] $end
$var reg 3 7 s[2:0] $end
$var reg 8 8 r[7:0] $end
$var reg 1 9 c $end
$var reg 1 : v $end
$var reg 1 ; z $end
$var reg 1 < sig $end
$var reg 8 = ap[7:0] $end
$var reg 8 > bp[7:0] $end
$var reg 1 ? cin $end
$var reg 8 @ r_aux[7:0] $end
$scope module sum $end
$var reg 8 A a[7:0] $end
$var reg 8 B b[7:0] $end
$var reg 1 C cin $end
$var reg 8 D r[7:0] $end
$var reg 1 E cout $end
$var reg 1 F v $end
$var reg 7 G c[6:0] $end
$var reg 1 H w $end
$scope module sumador0 $end
$var reg 1 I a $end
$var reg 1 J b $end
$var reg 1 K cin $end
$var reg 1 L r $end
$var reg 1 M cout $end
$upscope $end
$scope module sumador1 $end
$var reg 1 N a $end
$var reg 1 O b $end
$var reg 1 P cin $end
$var reg 1 Q r $end
$var reg 1 R cout $end
$upscope $end
$scope module sumador2 $end
$var reg 1 S a $end
$var reg 1 T b $end
$var reg 1 U cin $end
$var reg 1 V r $end
$var reg 1 W cout $end
$upscope $end
$scope module sumador3 $end
$var reg 1 X a $end
$var reg 1 Y b $end
$var reg 1 Z cin $end
$var reg 1 [ r $end
$var reg 1 \ cout $end
$upscope $end
$scope module sumador4 $end
$var reg 1 ] a $end
$var reg 1 ^ b $end
$var reg 1 _ cin $end
$var reg 1 ` r $end
$var reg 1 a cout $end
$upscope $end
$scope module sumador5 $end
$var reg 1 b a $end
$var reg 1 c b $end
$var reg 1 d cin $end
$var reg 1 e r $end
$var reg 1 f cout $end
$upscope $end
$scope module sumador6 $end
$var reg 1 g a $end
$var reg 1 h b $end
$var reg 1 i cin $end
$var reg 1 j r $end
$var reg 1 k cout $end
$upscope $end
$scope module sumador7 $end
$var reg 1 l a $end
$var reg 1 m b $end
$var reg 1 n cin $end
$var reg 1 o r $end
$var reg 1 p cout $end
$upscope $end
$upscope $end
$upscope $end
$scope module ul $end
$var reg 8 q a[7:0] $end
$var reg 8 r b[7:0] $end
$var reg 3 s s[2:0] $end
$var reg 8 t r[7:0] $end
$upscope $end
$scope module us $end
$var reg 8 u a[7:0] $end
$var reg 2 v s[1:0] $end
$var reg 8 w r[7:0] $end
$scope module mux7 $end
$var reg 1 x entrada0 $end
$var reg 1 y entrada1 $end
$var reg 1 z entrada2 $end
$var reg 1 { entrada3 $end
$var reg 2 | selector[1:0] $end
$var reg 1 } salida $end
$upscope $end
$scope module mux6 $end
$var reg 1 !" entrada0 $end
$var reg 1 "" entrada1 $end
$var reg 1 #" entrada2 $end
$var reg 1 $" entrada3 $end
$var reg 2 %" selector[1:0] $end
$var reg 1 &" salida $end
$upscope $end
$scope module mux5 $end
$var reg 1 '" entrada0 $end
$var reg 1 (" entrada1 $end
$var reg 1 )" entrada2 $end
$var reg 1 *" entrada3 $end
$var reg 2 +" selector[1:0] $end
$var reg 1 ," salida $end
$upscope $end
$scope module mux4 $end
$var reg 1 -" entrada0 $end
$var reg 1 ." entrada1 $end
$var reg 1 /" entrada2 $end
$var reg 1 0" entrada3 $end
$var reg 2 1" selector[1:0] $end
$var reg 1 2" salida $end
$upscope $end
$scope module mux3 $end
$var reg 1 3" entrada0 $end
$var reg 1 4" entrada1 $end
$var reg 1 5" entrada2 $end
$var reg 1 6" entrada3 $end
$var reg 2 7" selector[1:0] $end
$var reg 1 8" salida $end
$upscope $end
$scope module mux2 $end
$var reg 1 9" entrada0 $end
$var reg 1 :" entrada1 $end
$var reg 1 ;" entrada2 $end
$var reg 1 <" entrada3 $end
$var reg 2 =" selector[1:0] $end
$var reg 1 >" salida $end
$upscope $end
$scope module mux1 $end
$var reg 1 ?" entrada0 $end
$var reg 1 @" entrada1 $end
$var reg 1 A" entrada2 $end
$var reg 1 B" entrada3 $end
$var reg 2 C" selector[1:0] $end
$var reg 1 D" salida $end
$upscope $end
$scope module mux0 $end
$var reg 1 E" entrada0 $end
$var reg 1 F" entrada1 $end
$var reg 1 G" entrada2 $end
$var reg 1 H" entrada3 $end
$var reg 2 I" selector[1:0] $end
$var reg 1 J" salida $end
$upscope $end
$upscope $end
$upscope $end
$upscope $end
$enddefinitions $end
#0
b00000001 !
b00000010 "
b00000 #
b00000011 $
0%
0&
0'
0(
b00000001 )
b00000010 *
b00000 +
b00000011 ,
0-
0.
0/
00
b00000011 1
b11111110 2
b00000000 3
b00 4
b00000001 5
b00000010 6
b000 7
b00000011 8
09
0:
0;
0<
b00000001 =
b00000010 >
0?
b00000011 @
b00000001 A
b00000010 B
0C
b00000011 D
0E
0F
b0000000 G
0H
1I
0J
0K
1L
0M
0N
1O
0P
1Q
0R
0S
0T
0U
0V
0W
0X
0Y
0Z
0[
0\
0]
0^
0_
0`
0a
0b
0c
0d
0e
0f
0g
0h
0i
0j
0k
0l
0m
0n
0o
0p
b00000001 q
b00000010 r
b000 s
b11111110 t
b00000001 u
b00 v
b00000000 w
0x
0y
1z
0{
b00 |
0}
0!"
0""
0#"
0$"
b00 %"
0&"
0'"
0("
0)"
0*"
b00 +"
0,"
0-"
0."
0/"
00"
b00 1"
02"
03"
04"
05"
06"
b00 7"
08"
09"
0:"
0;"
0<"
b00 ="
0>"
0?"
1@"
0A"
1B"
b00 C"
0D"
0E"
0F"
0G"
0H"
b00 I"
0J"
#10000000
b01010101 !
b10101010 "
b00001 #
b10101011 $
1&
1(
b01010101 )
b10101010 *
b00001 +
b10101011 ,
1.
10
b10101011 1
b01010101 2
b10101010 3
b01010101 5
b10101010 6
b001 7
b10101011 8
1:
1<
b01010101 =
b01010101 >
1?
b10101011 @
b01010101 A
b01010101 B
1C
b10101011 D
1F
b1010101 G
1J
1K
1M
0O
1P
1Q
1S
1T
1W
1Z
1[
1]
1^
1a
1d
1e
1g
1h
1k
1n
1o
b01010101 q
b10101010 r
b001 s
b01010101 t
b01010101 u
b01 v
b10101010 w
1y
1{
b01 |
1}
b01 %"
1'"
1("
1)"
1*"
b01 +"
1,"
b01 1"
13"
14"
15"
16"
b01 7"
18"
b01 ="
1?"
1A"
b01 C"
1D"
b01 I"
#20000000
b11001100 !
b00000000 "
b00010 #
b11001101 $
0%
0&
1(
b11001100 )
b00000000 *
b00010 +
b11001101 ,
0-
0.
10
b11001101 1
b00000000 2
b01100110 3
b11001100 5
b00000000 6
b010 7
b11001101 8
09
0:
1<
b11001100 =
b00000000 >
b11001101 @
b11001100 A
b00000000 B
b11001101 D
0E
0F
b0000000 G
0H
0I
0J
0M
0P
0Q
0T
1V
0W
1X
0Z
1[
0\
0]
0^
0_
0`
0a
0d
0e
0h
1j
0k
1l
0n
1o
0p
b11001100 q
b00000000 r
b010 s
b00000000 t
b11001100 u
b10 v
b01100110 w
0z
b10 |
0}
1!"
1#"
b10 %"
1&"
0("
0*"
b10 +"
1."
10"
b10 1"
03"
05"
b10 7"
08"
19"
1;"
b10 ="
1>"
0@"
0B"
b10 C"
1H"
b10 I"
#30000000
b11111111 !
b00011 #
b00000001 $
0(
b11111111 )
b00011 +
b00000001 ,
00
b00000001 1
b11111111 2
b11111111 3
b11111111 5
b011 7
b00000001 8
0<
b00000000 =
b00000001 @
b00000000 A
b00000001 D
0S
0V
0X
0[
0g
0j
0l
0o
b11111111 q
b011 s
b11111111 t
b11111111 u
b11 v
b11111111 w
1z
b11 |
1}
1""
1$"
b11 %"
1("
1*"
b11 +"
1-"
1/"
b11 1"
12"
13"
15"
b11 7"
18"
1:"
1<"
b11 ="
1@"
1B"
b11 C"
1E"
1G"
b11 I"
1J"
#40000000
b00000001 !
b11111110 "
b00100 #
b00000000 $
1%
0&
1'
0(
b00000001 )
b11111110 *
b00100 +
b00000000 ,
1-
0.
1/
00
b00000000 1
b00000000 3
b00000001 5
b11111110 6
b100 7
b00000000 8
19
0:
1;
0<
b00000001 =
b11111111 >
0?
b00000000 @
b00000001 A
b11111111 B
0C
b00000000 D
1E
0F
b1111111 G
1H
1I
1J
0K
0L
1M
1O
1P
0Q
1R
1T
1U
0V
1W
1Y
1Z
0[
1\
1^
1_
0`
1a
1c
1d
0e
1f
1h
1i
0j
1k
1m
1n
0o
1p
b00000001 q
b11111110 r
b100 s
b00000001 u
b00 v
b00000000 w
0y
0{
b00 |
0}
0!"
0""
0#"
0$"
b00 %"
0&"
0'"
0("
0)"
0*"
b00 +"
0,"
0-"
0."
0/"
00"
b00 1"
02"
03"
04"
05"
06"
b00 7"
08"
09"
0:"
0;"
0<"
b00 ="
0>"
0?"
0A"
b00 C"
0D"
0E"
0G"
0H"
b00 I"
0J"
#50000000
b10101010 !
b01010101 "
b00101 #
b01010100 $
0'
b10101010 )
b01010101 *
b00101 +
b01010100 ,
0/
b01010100 1
b00000000 2
b01010100 3
b10101010 5
b01010101 6
b101 7
b01010100 8
0;
b11111111 =
b01010101 >
b01010100 @
b11111111 A
b01010101 B
b01010100 D
1N
0O
1S
1V
1X
0Y
1]
1`
1b
0c
1g
1j
1l
0m
b10101010 q
b01010101 r
b101 s
b00000000 t
b10101010 u
b01 v
b01010100 w
0z
b01 |
1!"
1""
1#"
1$"
b01 %"
1&"
b01 +"
1-"
1."
1/"
10"
b01 1"
12"
b01 7"
19"
1:"
1;"
1<"
b01 ="
1>"
0@"
0B"
b01 C"
1E"
1G"
1H"
b01 I"
#60000000
b01010101 !
b10101010 "
b00110 #
b01010101 $
0%
0&
0(
b01010101 )
b10101010 *
b00110 +
b01010101 ,
0-
0.
00
b01010101 1
b11111111 2
b10101010 3
b01010101 5
b10101010 6
b110 7
b01010101 8
09
0:
0<
b01010101 =
b00000000 >
b01010101 @
b01010101 A
b00000000 B
b01010101 D
0E
0F
b0000000 G
0H
0J
1L
0M
0N
0P
0Q
0R
0T
0U
1V
0W
0X
0Z
0[
0\
0^
0_
1`
0a
0b
0d
0e
0f
0h
0i
1j
0k
0l
0n
0o
0p
b01010101 q
b10101010 r
b110 s
b11111111 t
b01010101 u
b10 v
b10101010 w
1y
1z
1{
b10 |
1}
0!"
0""
0#"
0$"
b10 %"
0&"
1'"
1("
1)"
1*"
b10 +"
1,"
0-"
0."
0/"
00"
b10 1"
02"
13"
14"
15"
16"
b10 7"
18"
09"
0:"
0;"
0<"
b10 ="
0>"
1?"
1@"
1A"
1B"
b10 C"
1D"
0E"
0G"
0H"
b10 I"
#70000000
b11110000 !
b00001111 "
b00111 #
b00001111 $
b11110000 )
b00001111 *
b00111 +
b00001111 ,
b00001111 1
b00000000 2
b11100001 3
b11110000 5
b00001111 6
b111 7
b00001111 8
b00000000 =
b00001111 >
b00001111 @
b00000000 A
b00001111 B
b00001111 D
0I
1J
1O
1Q
0S
1T
1Y
1[
0]
0`
0g
0j
b11110000 q
b00001111 r
b111 s
b00000000 t
b11110000 u
b11 v
b11100001 w
0z
b11 |
1!"
1""
1#"
1$"
b11 %"
1&"
b11 +"
1-"
1/"
b11 1"
04"
06"
b11 7"
08"
b11 ="
0?"
0@"
0A"
0B"
b11 C"
0D"
1H"
b11 I"
1J"
#80000000
b11001100 !
b00110011 "
b01000 #
b00110011 $
1(
b11001100 )
b00110011 *
b01000 +
b00110011 ,
10
b11111111 1
b00110011 2
b01100110 3
b01 4
b11001100 5
b00110011 6
b000 7
b11111111 8
1<
b11001100 =
b00110011 >
b11111111 @
b11001100 A
b00110011 B
b11111111 D
1S
0T
1X
0Y
1^
1`
1c
1e
1g
1j
1l
1o
b11001100 q
b00110011 r
b000 s
b00110011 t
b11001100 u
b00 v
b01100110 w
b00 |
0}
0""
0$"
b00 %"
0("
0*"
b00 +"
0-"
1."
0/"
10"
b00 1"
03"
14"
05"
16"
b00 7"
19"
1;"
b00 ="
1>"
1?"
1A"
b00 C"
1D"
b00 I"
0J"
#90000000
b00110011 !
b11001100 "
b01001 #
0(
b00110011 )
b11001100 *
b01001 +
00
b01100111 1
b00110011 5
b11001100 6
b001 7
b01100111 8
0<
b00110011 =
1?
b01100111 @
b00110011 A
1C
b01100111 D
b0110011 G
1I
1K
1M
1N
1P
1Q
1R
0S
1U
1V
0X
0[
1]
0`
1a
1b
1d
1e
1f
0g
1i
1j
0l
0o
b00110011 q
b11001100 r
b001 s
b00110011 u
b01 v
0y
1z
0{
b01 |
0!"
1""
0#"
1$"
b01 %"
0'"
1("
0)"
1*"
b01 +"
1-"
0."
1/"
00"
b01 1"
13"
04"
15"
06"
b01 7"
09"
1:"
0;"
1<"
b01 ="
0?"
1@"
0A"
1B"
b01 C"
1E"
1G"
0H"
b01 I"
#100000000
b11111111 !
b00000001 "
b01010 #
b00000001 $
1%
0&
1'
0(
b11111111 )
b00000001 *
b01010 +
b00000001 ,
1-
0.
1/
00
b00000000 1
b00000001 2
b11111111 3
b11111111 5
b00000001 6
b010 7
b00000000 8
19
0:
1;
0<
b11111111 =
b00000000 >
b00000000 @
b11111111 A
b00000000 B
b00000000 D
1E
0F
b1111111 G
1H
0J
0L
0O
0Q
1S
0V
1W
1X
1Z
0[
1\
0^
1_
0`
1a
0c
1d
0e
1f
1g
1i
0j
1k
1l
1n
0o
1p
b11111111 q
b00000001 r
b010 s
b00000001 t
b11111111 u
b10 v
b11111111 w
1y
1{
b10 |
1}
1!"
1#"
b10 %"
1'"
1)"
b10 +"
1."
10"
b10 1"
12"
14"
16"
b10 7"
18"
19"
1;"
b10 ="
1?"
1A"
b10 C"
1H"
b10 I"
1J"
#110000000
b00000010 !
b11111111 "
b01011 #
b11111111 $
b00000010 )
b11111111 *
b01011 +
b11111111 ,
b11111111 2
b00000100 3
b00000010 5
b11111111 6
b011 7
b00000000 =
b11111111 >
b00000000 A
b11111111 B
0I
1J
0N
1O
0S
1T
0X
1Y
0]
1^
0b
1c
0g
1h
0l
1m
b00000010 q
b11111111 r
b011 s
b11111111 t
b00000010 u
b11 v
b00000100 w
0y
0z
0{
b11 |
0}
0!"
0""
0#"
0$"
b11 %"
0&"
0'"
0("
0)"
0*"
b11 +"
0,"
0-"
0."
0/"
00"
b11 1"
02"
03"
04"
05"
06"
b11 7"
08"
09"
0;"
b11 ="
0?"
0@"
0A"
0B"
b11 C"
0D"
0H"
b11 I"
0J"
#120000000
b10101010 !
b01010101 "
b01100 #
0'
1(
b10101010 )
b01010101 *
b01100 +
0/
10
b10101001 1
b01010101 3
b10101010 5
b01010101 6
b100 7
b10101001 8
0;
1<
b10101010 =
0?
b10101001 @
b10101010 A
0C
b10101001 D
b1111110 G
0K
1L
0M
1N
0P
0Q
1X
1[
1b
1e
1l
1o
b10101010 q
b01010101 r
b100 s
b10101010 u
b00 v
b01010101 w
b00 |
1!"
1""
1#"
1$"
b00 %"
1&"
b00 +"
1-"
1."
1/"
10"
b00 1"
12"
b00 7"
19"
1;"
b00 ="
b00 C"
1H"
b00 I"
1J"
#130000000
b01010101 !
b10101010 "
b01101 #
b00000000 $
b01010101 )
b10101010 *
b01101 +
b00000000 ,
b00000000 2
b10101010 3
b01010101 5
b10101010 6
b101 7
b11111111 =
b10101010 >
b11111111 A
b10101010 B
1I
0J
1S
0T
1]
0^
1g
0h
b01010101 q
b10101010 r
b101 s
b00000000 t
b01010101 u
b01 v
b10101010 w
1y
1z
1{
b01 |
1}
0!"
0""
0#"
0$"
b01 %"
0&"
1'"
1("
1)"
1*"
b01 +"
1,"
0-"
0."
0/"
00"
b01 1"
02"
13"
14"
15"
16"
b01 7"
18"
09"
0:"
0;"
0<"
b01 ="
0>"
1?"
1@"
1A"
1B"
b01 C"
1D"
0E"
0G"
0H"
b01 I"
0J"
